README.md
setup.py
jiucai/__init__.py
jiucai.egg-info/PKG-INFO
jiucai.egg-info/SOURCES.txt
jiucai.egg-info/dependency_links.txt
jiucai.egg-info/top_level.txt