Metadata-Version: 2.1
Name: jiucai
Version: 0.0.0
Summary: jiucai
Home-page: UNKNOWN
Author: yanyan
Author-email: shiyanaimama@163.com
License: UNKNOWN
Platform: UNKNOWN
Classifier: Programming Language :: Python :: 3
Classifier: License :: OSI Approved :: MIT License
Classifier: Operating System :: OS Independent
